get_5c_cdr/main.py
get_5c_cdr-0.1.4.dist-info/METADATA
get_5c_cdr-0.1.4.dist-info/WHEEL
get_5c_cdr-0.1.4.dist-info/entry_points.txt
get_5c_cdr-0.1.4.dist-info/RECORD
