Metadata-Version: 2.3
Name: get-5c-cdr
Version: 0.1.4
Summary: 
Author: 6vi7ms
Author-email: 6vi7ms@gmail.com
Requires-Python: >=3.13
Classifier: Programming Language :: Python :: 3
Classifier: Programming Language :: Python :: 3.13
Requires-Dist: browsercookie (>=0.8.1,<0.9.0)
Requires-Dist: openpyxl (>=3.1.5,<4.0.0)
Requires-Dist: pandas (>=2.3.1,<3.0.0)
Requires-Dist: requests (>=2.32.4,<3.0.0)
Requires-Dist: tqdm (>=4.67.1,<5.0.0)
